NdbSearchableBase
