Metadata-Version: 1.0
Name: NdbSearchableBase
Version: 1.2
Summary: Searchable Base Model for NDB
Home-page: https://github.com/kkinder/NdbSearchableBase
Author: Ken Kinder
Author-email: ken@kkinder.com
License: Apache License 2.0
Keywords: google-app-engine,ndb,full-text,search,indexing
Platform: UNKNOWN
